{
  "scriptCompleted": true,
  "filesAnalyzed": 3,
  "filesSkipped": [],
  "results": [
    {
      "path": "backend/AGENTS.md",
      "language": "markdown",
      "fileCategory": "docs",
      "totalLines": 178,
      "nonEmptyLines": 152,
      "sections": [
        {
          "heading": "Backend",
          "level": 1,
          "line": 1
        },
        {
          "heading": "Purpose",
          "level": 2,
          "line": 3
        },
        {
          "heading": "Ownership",
          "level": 2,
          "line": 7
        },
        {
          "heading": "Local Contracts",
          "level": 2,
          "line": 11
        },
        {
          "heading": "Internal Package Layout",
          "level": 3,
          "line": 27
        },
        {
          "heading": "Classification Loop (daemon mode)",
          "level": 3,
          "line": 46
        },
        {
          "heading": "API Contract (consumed by frontend)",
          "level": 3,
          "line": 60
        },
        {
          "heading": "Environment Variables",
          "level": 3,
          "line": 107
        },
        {
          "heading": "Key Data Files",
          "level": 3,
          "line": 128
        },
        {
          "heading": "Log Files",
          "level": 3,
          "line": 149
        },
        {
          "heading": "Work Guidance",
          "level": 2,
          "line": 161
        },
        {
          "heading": "Verification",
          "level": 2,
          "line": 169
        },
        {
          "heading": "Child DOX Index",
          "level": 2,
          "line": 174
        }
      ],
      "metrics": {
        "importCount": 0,
        "exportCount": 0,
        "functionCount": 0,
        "classCount": 0,
        "sectionCount": 13
      }
    },
    {
      "path": "backend/go.mod",
      "language": "mod",
      "fileCategory": "config",
      "totalLines": 48,
      "nonEmptyLines": 44,
      "metrics": {}
    },
    {
      "path": "backend/go.sum",
      "language": "sum",
      "fileCategory": "config",
      "totalLines": 156,
      "nonEmptyLines": 156,
      "metrics": {}
    }
  ]
}